djinni/__init__.py
djinni/exception.py
djinni/pycffi_marshal.py
djinni/support.py
djinni-1.2.0.dist-info/LICENSE
djinni-1.2.0.dist-info/METADATA
djinni-1.2.0.dist-info/WHEEL
djinni-1.2.0.dist-info/top_level.txt
djinni-1.2.0.dist-info/RECORD
